what_vpn/__main__.py
what_vpn/requests.py
what_vpn/sniffers.py
what_vpn/version.py
what_vpn-0.7.dist-info/METADATA
what_vpn-0.7.dist-info/WHEEL
what_vpn-0.7.dist-info/entry_points.txt
what_vpn-0.7.dist-info/top_level.txt
what_vpn-0.7.dist-info/RECORD
