Metadata-Version: 2.1
Name: what-vpn
Version: 0.7
Summary: Identify servers running various SSL VPNs
Home-page: https://github.com/dlenski/what-vpn
Author: Daniel Lenski
Author-email: dlenski@gmail.com
License: GPL v3 or later
Classifier: License :: OSI Approved :: GNU General Public License v3 or later (GPLv3+)
Classifier: Development Status :: 4 - Beta
Classifier: Topic :: System :: Networking
Classifier: Environment :: Console
Requires-Dist: requests (>=2.0.0)
Requires-Dist: attrs (>=15.0)
